MANIFEST.in
README.rst
requirements.txt
setup.cfg
setup.py
pynso/__init__.py
pynso/client.py
pynso/connection.py
pynso/datastores.py
pynso/resourcetypes.py
pynso.egg-info/PKG-INFO
pynso.egg-info/SOURCES.txt
pynso.egg-info/dependency_links.txt
pynso.egg-info/requires.txt
pynso.egg-info/top_level.txt