Metadata-Version: 1.1
Name: pynso
Version: 1.2.0
Summary: A Python client library for Cisco NSO (previously tail-f)
Home-page: https://github.com/DimensionDataCBUSydney/pynso
Author: Anthony Shaw
Author-email: anthony.shaw@dimensiondata.com
License: APACHE2
Download-URL: https://github.com/tonybaloney/DimensionDataCBUSydney/tarball/1.2.0
Platform: UNKNOWN
Classifier: Development Status :: 3 - Alpha
Classifier: Intended Audience :: Developers
Classifier: Programming Language :: Python :: 3
Classifier: Programming Language :: Python :: 2
